configr/__init__.py
configr/base.py
configr/config_class.py
configr/exceptions.py
configr/field_type_checker.py
configr/utils.py
configr/loaders/__init__.py
configr/loaders/loader_base.py
configr/loaders/loader_dotenv.py
configr/loaders/loader_env_var.py
configr/loaders/loader_json.py
configr/loaders/loader_yaml.py
py_configr-0.5.0.dist-info/licenses/LICENSE
py_configr-0.5.0.dist-info/METADATA
py_configr-0.5.0.dist-info/WHEEL
py_configr-0.5.0.dist-info/top_level.txt
py_configr-0.5.0.dist-info/RECORD
