Metadata-Version: 2.4
Name: py-configr
Version: 0.5.0
Summary: A flexible, type-safe configuration management library for Python
Author-email: Corinna Wieken <5384689+cwieken@users.noreply.github.com>
License-Expression: MIT
Project-URL: Homepage, https://github.com/cwieken/configr
Project-URL: Bug Tracker, https://github.com/cwieken/configr/issues
Classifier: Programming Language :: Python :: 3
Classifier: Operating System :: OS Independent
Requires-Python: <3.14,>=3.10
License-File: LICENSE
Provides-Extra: yaml
Requires-Dist: pyyaml>=6.0; extra == "yaml"
Provides-Extra: dotenv
Requires-Dist: python-dotenv>=1.0.0; extra == "dotenv"
Dynamic: license-file
